fracdiff/__init__.py
fracdiff/fdiff.py
fracdiff/sklearn/__init__.py
fracdiff/sklearn/fracdiff.py
fracdiff/sklearn/fracdiffstat.py
fracdiff/sklearn/stat.py
fracdiff/sklearn/tol.py
fracdiff/torch/__init__.py
fracdiff/torch/functional.py
fracdiff/torch/module.py
fracdiff-0.9.0.dist-info/LICENSE
fracdiff-0.9.0.dist-info/WHEEL
fracdiff-0.9.0.dist-info/METADATA
fracdiff-0.9.0.dist-info/RECORD
